Workbook

Sheet Cover
A1: SYNTHETIC / ILLUSTRATIVE DATA. Fictional company. Not based on any real business. For demo and testing only.
A3: Example Event Services Holdings ("Platform A")
A4: Monthly Reporting Package: September 2026
A5: Prepared by: Corporate Controller
A6: Sent to sponsor: October 20, 2026 (business day 14 after month-end)
A7: Basis: Accrual, unaudited, management accounts
A8: Scope: Platform A standalone. Add-on B (acquired June 1, 2026) reports separately until its systems migrate (planned Q1 2027).
A10: Contents
A11: 1. CEO Letter
A12: 2. Summary
A13: 3. P&L (month and YTD vs budget and prior year)
A14: 4. P&L Trend (trailing twelve months)
... A20: 10. Covenant Compliance

Sheet CEO Letter
A1: SYNTHETIC / ILLUSTRATIVE DATA. Fictional company. Not based on any real business. For demo and testing only.
A3: September 2026 CEO Letter
A5: September was our strongest revenue month on record, driven by the start of the fall stadium season and two new convention center accounts.
A6: Fill rate improved to 97% as our recruiting investments paid off, and we held gross margin in line with plan despite continued wage pressure.
A7: Integration of Add-on B is complete, and we expect to begin realizing the $2.1M of run-rate synergies identified in diligence during Q4.
A8: We incurred one-time recruiting costs in August and September to staff the season, which are added back in Adjusted EBITDA.
A9: Diligence continues on Project Falcon, a potential second add-on in an adjacent market. Related professional fees are added back.
A10: We remain comfortably within our leverage covenant.
A12: CEO, Platform A

Sheet P&L
A1: SYNTHETIC / ILLUSTRATIVE DATA. Fictional company. Not based on any real business. For demo and testing only.
A2: Platform A: P&L, September 2026 ($)
A3: Actuals link to P&L Trend (green). Budget and prior year are hardcoded (blue).
A5: Line item | B5: Sep-26 Actual | C5: Sep-26 Budget | D5: Var $ | E5: Var % | F5: Sep-25 Actual | G5: YTD Actual | H5: YTD Budget | I5: Var $ | J5: Var % | K5: YTD Prior Year
A6: Revenue
A7: Event Staffing Revenue | B7: ='P&L Trend'!M6 -> 4513673 | C7: 4620000 | D7: =B7-C7 -> -106327 | E7: =IF(C7=0,0,D7/ABS(C7)) -> -0.023014502 | F7: 4126596 | G7: =SUM('P&L Trend'!E6:M6) -> 34140161 | H7: 34611500 | I7: =G7-H7 -> -471339 | J7: =IF(H7=0,0,I7/ABS(H7)) -> -0.013617988 | K7: 30923491
A8: Security & Patrol Revenue | B8: ='P&L Trend'!M7 -> 666848 | C8: 660000 | D8: =B8-C8 -> 6848 | E8: =IF(C8=0,0,D8/ABS(C8)) -> 0.010375758 | F8: 602776 | G8: =SUM('P&L Trend'!E7:M7) -> 5938728 | H8: 5940000 | I8: =G8-H8 -> -1272 | J8: =IF(H8=0,0,I8/ABS(H8)) -> -0.00021414141 | K8: 5481178
A9: Other Revenue (Box Office, Convention) | B9: ='P&L Trend'!M8 -> 203231 | C9: 207900 | D9: =B9-C9 -> -4669 | E9: =IF(C9=0,0,D9/ABS(C9)) -> -0.022457912 | F9: 184036 | G9: =SUM('P&L Trend'!E8:M8) -> 1544967 | H9: 1557518 | I9: =G9-H9 -> -12551 | J9: =IF(H9=0,0,I9/ABS(H9)) -> -0.0080583338 | K9: 1390150
A10: Total Revenue | B10: =SUM(B7:B9) -> 5383752 | C10: =SUM(C7:C9) -> 5487900 | D10: =B10-C10 -> -104148 | E10: =IF(C10=0,0,D10/ABS(C10)) -> -0.018977751 | F10: =SUM(F7:F9) -> 4913408 | G10: =SUM(G7:G9) -> 41623856 | H10: =SUM(H7:H9) -> 42109018 | I10: =G10-H10 -> -485162 | J10: =IF(H10=0,0,I10/ABS(H10)) -> -0.01152157 | K10: =SUM(K7:K9) -> 37794819
A12: Direct Costs
A13: Direct Labor - Wages | B13: ='P&L Trend'!M12 -> 2967646 | C13: 2885318 | D13: =B13-C13 -> 82328 | E13: =IF(C13=0,0,D13/ABS(C13)) -> 0.028533423 | F13: 2569305 | G13: =SUM('P&L Trend'!E12:M12) -> 22539093 | H13: 22163365 | I13: =G13-H13 -> 375728 | J13: =IF(H13=0,0,I13/ABS(H13)) -> 0.01695266 | K13: 19783892
A14: Payroll Taxes & Benefits | B14: ='P&L Trend'!M13 -> 311603 | C14: 302958 | D14: =B14-C14 -> 8645 | E14: =IF(C14=0,0,D14/ABS(C14)) -> 0.028535309 | F14: 269777 | G14: =SUM('P&L Trend'!E13:M13) -> 2366605 | H14: 2327152 | I14: =G14-H14 -> 39453 | J14: =IF(H14=0,0,I14/ABS(H14)) -> 0.01695334 | K14: 2077308
A15: Workers' Compensation | B15: ='P&L Trend'!M14 -> 207735 | C15: 201972 | D15: =B15-C15 -> 5763 | E15: =IF(C15=0,0,D15/ABS(C15)) -> 0.028533658 | F15: 179851 | G15: =SUM('P&L Trend'!E14:M14) -> 1577736 | H15: 1551436 | I15: =G15-H15 -> 26300 | J15: =IF(H15=0,0,I15/ABS(H15)) -> 0.016952037 | K15: 1384873
A16: Subcontracted Labor | B16: ='P&L Trend'!M15 -> 323025 | C16: 126222 | D16: =B16-C16 -> 196803 | E16: =IF(C16=0,0,D16/ABS(C16)) -> 1.5591814 | F16: 122835 | G16: =SUM('P&L Trend'!E15:M15) -> 1330719 | H16: 968508 | I16: =G16-H16 -> 362211 | J16: =IF(H16=0,0,I16/ABS(H16)) -> 0.37398865 | K16: 944871
A17: Uniforms & Equipment | B17: ='P&L Trend'!M16 -> 32303 | C17: 32927 | D17: =B17-C17 -> -624 | E17: =IF(C17=0,0,D17/ABS(C17)) -> -0.018951013 | F17: 29480 | G17: =SUM('P&L Trend'!E16:M16) -> 249743 | H17: 252653 | I17: =G17-H17 -> -2910 | J17: =IF(H17=0,0,I17/ABS(H17)) -> -0.011517773 | K17: 226767
A18: Event Travel & Transport | B18: ='P&L Trend'!M17 -> 43070 | C18: 43903 | D18: =B18-C18 -> -833 | E18: =IF(C18=0,0,D18/ABS(C18)) -> -0.018973646 | F18: 39307 | G18: =SUM('P&L Trend'!E17:M17) -> 332990 | H18: 336872 | I18: =G18-H18 -> -3882 | J18: =IF(H18=0,0,I18/ABS(H18)) -> -0.011523665 | K18: 302359
A19: Total Direct Costs | B19: =SUM(B13:B18) -> 3885382 | C19: =SUM(C13:C18) -> 3593300 | D19: =B19-C19 -> 292082 | E19: =IF(C19=0,0,D19/ABS(C19)) -> 0.08128517 | F19: =SUM(F13:F18) -> 3210555 | G19: =SUM(G13:G18) -> 28396886 | H19: =SUM(H13:H18) -> 27599986 | I19: =G19-H19 -> 796900 | J19: =IF(H19=0,0,I19/ABS(H19)) -> 0.028873203 | K19: =SUM(K13:K18) -> 24720070
A20: Gross Profit | B20: =B10-B19 -> 1498370 | C20: =C10-C19 -> 1894600 | D20: =B20-C20 -> -396230 | E20: =IF(C20=0,0,D20/ABS(C20)) -> -0.20913649 | F20: =F10-F19 -> 1702853 | G20: =G10-G19 -> 13226970 | H20: =H10-H19 -> 14509032 | I20: =G20-H20 -> -1282062 | J20: =IF(H20=0,0,I20/ABS(H20)) -> -0.088363028 | K20: =K10-K19 -> 13074749
A21: Gross Margin % | B21: =IF(B10=0,0,B20/B10) -> 0.27831334 | C21: =IF(C10=0,0,C20/C10) -> 0.34523224 | F21: =IF(F10=0,0,F20/F10) -> 0.34657268 | G21: =IF(G10=0,0,G20/G10) -> 0.31777378 | H21: =IF(H10=0,0,H20/H10) -> 0.34455878 | K21: =IF(K10=0,0,K20/K10) -> 0.34594025
A23: SG&A
A24: Salaries - Admin & Management | B24: ='P&L Trend'!M23 -> 455000 | C24: 430000 | D24: =B24-C24 -> 25000 | E24: =IF(C24=0,0,D24/ABS(C24)) -> 0.058139535 | F24: 405000 | G24: =SUM('P&L Trend'!E23:M23) -> 4015000 | H24: 3870000 | I24: =G24-H24 -> 145000 | J24: =IF(H24=0,0,I24/ABS(H24)) -> 0.0374677 | K24: 3645000
A25: Recruiting & Onboarding | B25: ='P&L Trend'!M24 -> 96908 | C25: 65855 | D25: =B25-C25 -> 31053 | E25: =IF(C25=0,0,D25/ABS(C25)) -> 0.47153595 | F25: 58961 | G25: =SUM('P&L Trend'!E24:M24) -> 562296 | H25: 505308 | I25: =G25-H25 -> 56988 | J25: =IF(H25=0,0,I25/ABS(H25)) -> 0.11277874 | K25: 453539
A26: Rent & Occupancy | B26: ='P&L Trend'!M25 -> 45000 | C26: 45000 | D26: =B26-C26 -> 0 | E26: =IF(C26=0,0,D26/ABS(C26)) -> 0 | F26: 45000 | G26: =SUM('P&L Trend'!E25:M25) -> 405000 | H26: 405000 | I26: =G26-H26 -> 0 | J26: =IF(H26=0,0,I26/ABS(H26)) -> 0 | K26: 405000
A27: Insurance (GL / Umbrella) | B27: ='P&L Trend'!M26 -> 68000 | C27: 68000 | D27: =B27-C27 -> 0 | E27: =IF(C27=0,0,D27/ABS(C27)) -> 0 | F27: 68000 | G27: =SUM('P&L Trend'!E26:M26) -> 612000 | H27: 612000 | I27: =G27-H27 -> 0 | J27: =IF(H27=0,0,I27/ABS(H27)) -> 0 | K27: 612000
A28: Software & IT | B28: ='P&L Trend'!M27 -> 36000 | C28: 36000 | D28: =B28-C28 -> 0 | E28: =IF(C28=0,0,D28/ABS(C28)) -> 0 | F28: 36000 | G28: =SUM('P&L Trend'!E27:M27) -> 324000 | H28: 324000 | I28: =G28-H28 -> 0 | J28: =IF(H28=0,0,I28/ABS(H28)) -> 0 | K28: 324000
A29: Professional Fees | B29: ='P&L Trend'!M28 -> 178000 | C29: 38000 | D29: =B29-C29 -> 140000 | E29: =IF(C29=0,0,D29/ABS(C29)) -> 3.6842105 | F29: 38000 | G29: =SUM('P&L Trend'!E28:M28) -> 542000 | H29: 342000 | I29: =G29-H29 -> 200000 | J29: =IF(H29=0,0,I29/ABS(H29)) -> 0.58479532 | K29: 342000
A30: Travel & Entertainment | B30: ='P&L Trend'!M29 -> 24000 | C30: 24000 | D30: =B30-C30 -> 0 | E30: =IF(C30=0,0,D30/ABS(C30)) -> 0 | F30: 24000 | G30: =SUM('P&L Trend'!E29:M29) -> 216000 | H30: 216000 | I30: =G30-H30 -> 0 | J30: =IF(H30=0,0,I30/ABS(H30)) -> 0 | K30: 216000
A31: Marketing | B31: ='P&L Trend'!M30 -> 14000 | C31: 14000 | D31: =B31-C31 -> 0 | E31: =IF(C31=0,0,D31/ABS(C31)) -> 0 | F31: 14000 | G31: =SUM('P&L Trend'!E30:M30) -> 126000 | H31: 126000 | I31: =G31-H31 -> 0 | J31: =IF(H31=0,0,I31/ABS(H31)) -> 0 | K31: 126000
A32: Sponsor Monitoring Fee | B32: ='P&L Trend'!M31 -> 62500 | C32: 62500 | D32: =B32-C32 -> 0 | E32: =IF(C32=0,0,D32/ABS(C32)) -> 0 | F32: 62500 | G32: =SUM('P&L Trend'!E31:M31) -> 562500 | H32: 562500 | I32: =G32-H32 -> 0 | J32: =IF(H32=0,0,I32/ABS(H32)) -> 0 | K32: 562500
A33: Other G&A | B33: ='P&L Trend'!M32 -> 58000 | C33: 28000 | D33: =B33-C33 -> 30000 | E33: =IF(C33=0,0,D33/ABS(C33)) -> 1.0714286 | F33: 28000 | G33: =SUM('P&L Trend'!E32:M32) -> 372000 | H33: 252000 | I33: =G33-H33 -> 120000 | J33: =IF(H33=0,0,I33/ABS(H33)) -> 0.47619048 | K33: 252000
A34: Total SG&A | B34: =SUM(B24:B33) -> 1037408 | C34: =SUM(C24:C33) -> 811355 | D34: =B34-C34 -> 226053 | E34: =IF(C34=0,0,D34/ABS(C34)) -> 0.27861171 | F34: =SUM(F24:F33) -> 779461 | G34: =SUM(G24:G33) -> 7736796 | H34: =SUM(H24:H33) -> 7214808 | I34: =G34-H34 -> 521988 | J34: =IF(H34=0,0,I34/ABS(H34)) -> 0.072349534 | K34: 6963039
A36: EBITDA (reported) | B36: =B20-B34 -> 460962 | C36: =C20-C34 -> 1083245 | D36: =B36-C36 -> -622283 | E36: =IF(C36=0,0,D36/ABS(C36)) -> -0.57446192 | F36: =F20-F34 -> 923392 | G36: =G20-G34 -> 5490174 | H36: =H20-H34 -> 7294224 | I36: =G36-H36 -> -1804050 | J36: =IF(H36=0,0,I36/ABS(H36)) -> -0.24732583 | K36: =K20-K34 -> 6111710
A37: EBITDA Margin % | B37: =IF(B10=0,0,B36/B10) -> 0.085620957 | C37: =IF(C10=0,0,C36/C10) -> 0.19738789 | F37: =IF(F10=0,0,F36/F10) -> 0.1879331 | G37: =IF(G10=0,0,G36/G10) -> 0.1318997 | H37: =IF(H10=0,0,H36/H10) -> 0.17322237 | K37: =IF(K10=0,0,K36/K10) -> 0.16170761

Sheet P&L Trend
A1: SYNTHETIC / ILLUSTRATIVE DATA. Fictional company. Not based on any real business. For demo and testing only.
A2: Platform A: P&L by month, trailing twelve months ($)
A4: Line item | B4: Oct-25 | C4: Nov-25 | D4: Dec-25 | E4: Jan-26 | F4: Feb-26 | G4: Mar-26 | H4: Apr-26 | I4: May-26 | J4: Jun-26 | K4: Jul-26 | L4: Aug-26 | M4: Sep-26 | N4: LTM
A5: Revenue
A6: Event Staffing Revenue | B6: 3795946 | C6: 3300749 | D6: 3092832 | E6: 2627915 | F6: 2772557 | G6: 3248641 | H6: 3769179 | I6: 4178653 | J6: 4365386 | K6: 4427158 | L6: 4236999 | M6: 4513673 | N6: =SUM(B6:M6) -> 44329688
A7: Security & Patrol Revenue | B7: 618607 | C7: 614676 | D7: 618972 | E7: 663689 | F7: 660414 | G7: 666701 | H7: 664850 | I7: 651550 | J7: 655436 | K7: 654139 | L7: 655101 | M7: 666848 | N7: =SUM(B7:M7) -> 7790983
A8: Other Revenue (Box Office, Convention) | B8: 171665 | C8: 149959 | D8: 138092 | E8: 117923 | F8: 125881 | G8: 148205 | H8: 171749 | I8: 190224 | J8: 194089 | K8: 201182 | L8: 192483 | M8: 203231 | N8: =SUM(B8:M8) -> 2004683
A9: Total Revenue | B9: =SUM(B6:B8) -> 4586218 | C9: =SUM(C6:C8) -> 4065384 | D9: =SUM(D6:D8) -> 3849896 | E9: =SUM(E6:E8) -> 3409527 | F9: =SUM(F6:F8) -> 3558852 | G9: =SUM(G6:G8) -> 4063547 | H9: =SUM(H6:H8) -> 4605778 | I9: =SUM(I6:I8) -> 5020427 | ... N9: =SUM(N6:N8) -> 54125354
A11: Direct Costs
A12: Direct Labor - Wages | B12: 2398706 | C12: 2128008 | D12: 2017621 | E12: 1840795 | F12: 1920220 | G12: 2191034 | H12: 2482336 | I12: 2704970 | J12: 2811972 | K12: 2845948 | L12: 2774172 | M12: 2967646 | N12: =SUM(B12:M12) -> 29083428
A13: Payroll Taxes & Benefits | B13: 251864 | C13: 223441 | D13: 211850 | E13: 193283 | F13: 201623 | G13: 230059 | H13: 260645 | I13: 284022 | J13: 295257 | K13: 298825 | L13: 291288 | M13: 311603 | N13: =SUM(B13:M13) -> 3053760
A14: Workers' Compensation | B14: 167909 | C14: 148961 | D14: 141233 | E14: 128856 | F14: 134415 | G14: 153372 | H14: 173764 | I14: 189348 | J14: 196838 | K14: 199216 | L14: 194192 | M14: 207735 | N14: =SUM(B14:M14) -> 2035839
A15: Subcontracted Labor | B15: 114655 | C15: 101635 | D15: 96247 | E15: 85238 | F15: 88971 | G15: 101589 | H15: 115144 | I15: 125511 | J15: 130373 | K15: 132062 | L15: 228806 | M15: 323025 | N15: =SUM(B15:M15) -> 1643256
A16: Uniforms & Equipment | B16: 27517 | C16: 24392 | D16: 23099 | E16: 20457 | F16: 21353 | G16: 24381 | H16: 27635 | I16: 30123 | J16: 31289 | K16: 31695 | L16: 30507 | M16: 32303 | N16: =SUM(B16:M16) -> 324751
A17: Event Travel & Transport | B17: 36690 | C17: 32523 | D17: 30799 | E17: 27276 | F17: 28471 | G17: 32508 | H17: 36846 | I17: 40163 | J17: 41719 | K17: 42260 | L17: 40677 | M17: 43070 | N17: =SUM(B17:M17) -> 433002
A18: Total Direct Costs | B18: =SUM(B12:B17) -> 2997341 | C18: =SUM(C12:C17) -> 2658960 | D18: =SUM(D12:D17) -> 2520849 | E18: =SUM(E12:E17) -> 2295905 | F18: =SUM(F12:F17) -> 2395053 | G18: =SUM(G12:G17) -> 2732943 | H18: =SUM(H12:H17) -> 3096370 | I18: =SUM(I12:I17) -> 3374137 | ... N18: =SUM(N12:N17) -> 36574036
A19: Gross Profit | B19: =B9-B18 -> 1588877 | C19: =C9-C18 -> 1406424 | D19: =D9-D18 -> 1329047 | E19: =E9-E18 -> 1113622 | F19: =F9-F18 -> 1163799 | G19: =G9-G18 -> 1330604 | H19: =H9-H18 -> 1509408 | I19: =I9-I18 -> 1646290 | ... N19: =N9-N18 -> 17551318
A20: Gross Margin % | B20: =IF(B9=0,0,B19/B9) -> 0.34644603 | C20: =IF(C9=0,0,C19/C9) -> 0.34595108 | D20: =IF(D9=0,0,D19/D9) -> 0.34521634 | E20: =IF(E9=0,0,E19/E9) -> 0.32662067 | F20: =IF(F9=0,0,F19/F9) -> 0.32701528 | G20: =IF(G9=0,0,G19/G9) -> 0.3274489 | H20: =IF(H9=0,0,H19/H9) -> 0.32772053 | I20: =IF(I9=0,0,I19/I9) -> 0.32791832 | ... N20: =IF(N9=0,0,N19/N9) -> 0.32427165
A22: SG&A
A23: Salaries - Admin & Management | B23: 405000 | C23: 405000 | D23: 405000 | E23: 430000 | F23: 430000 | G23: 475000 | H23: 430000 | I23: 430000 | J23: 455000 | K23: 455000 | L23: 455000 | M23: 455000 | N23: =SUM(B23:M23) -> 5230000
A24: Recruiting & Onboarding | B24: 55035 | C24: 48785 | D24: 46199 | E24: 40914 | F24: 42706 | G24: 48763 | H24: 55269 | I24: 60245 | J24: 62579 | K24: 63390 | L24: 91522 | M24: 96908 | N24: =SUM(B24:M24) -> 712315
A25: Rent & Occupancy | B25: 45000 | C25: 45000 | D25: 45000 | E25: 45000 | F25: 45000 | G25: 45000 | H25: 45000 | I25: 45000 | J25: 45000 | K25: 45000 | L25: 45000 | M25: 45000 | N25: =SUM(B25:M25) -> 540000
A26: Insurance (GL / Umbrella) | B26: 68000 | C26: 68000 | D26: 68000 | E26: 68000 | F26: 68000 | G26: 68000 | H26: 68000 | I26: 68000 | J26: 68000 | K26: 68000 | L26: 68000 | M26: 68000 | N26: =SUM(B26:M26) -> 816000
A27: Software & IT | B27: 36000 | C27: 36000 | D27: 36000 | E27: 36000 | F27: 36000 | G27: 36000 | H27: 36000 | I27: 36000 | J27: 36000 | K27: 36000 | L27: 36000 | M27: 36000 | N27: =SUM(B27:M27) -> 432000
A28: Professional Fees | B28: 38000 | C28: 38000 | D28: 38000 | E28: 38000 | F28: 38000 | G28: 38000 | H28: 38000 | I28: 38000 | J28: 98000 | K28: 38000 | L28: 38000 | M28: 178000 | N28: =SUM(B28:M28) -> 656000
A29: Travel & Entertainment | B29: 24000 | C29: 24000 | D29: 24000 | E29: 24000 | F29: 24000 | G29: 24000 | H29: 24000 | I29: 24000 | J29: 24000 | K29: 24000 | L29: 24000 | M29: 24000 | N29: =SUM(B29:M29) -> 288000
A30: Marketing | B30: 14000 | C30: 14000 | D30: 14000 | E30: 14000 | F30: 14000 | G30: 14000 | H30: 14000 | I30: 14000 | J30: 14000 | K30: 14000 | L30: 14000 | M30: 14000 | N30: =SUM(B30:M30) -> 168000
A31: Sponsor Monitoring Fee | B31: 62500 | C31: 62500 | D31: 62500 | E31: 62500 | F31: 62500 | G31: 62500 | H31: 62500 | I31: 62500 | J31: 62500 | K31: 62500 | L31: 62500 | M31: 62500 | N31: =SUM(B31:M31) -> 750000
A32: Other G&A | B32: 28000 | C32: 28000 | D32: 28000 | E32: 28000 | F32: 28000 | G32: 28000 | H32: 28000 | I32: 28000 | J32: 58000 | K32: 58000 | L32: 58000 | M32: 58000 | N32: =SUM(B32:M32) -> 456000
A33: Total SG&A | B33: =SUM(B23:B32) -> 775535 | C33: =SUM(C23:C32) -> 769285 | D33: =SUM(D23:D32) -> 766699 | E33: =SUM(E23:E32) -> 786414 | F33: =SUM(F23:F32) -> 788206 | G33: =SUM(G23:G32) -> 839263 | H33: =SUM(H23:H32) -> 800769 | I33: =SUM(I23:I32) -> 805745 | ... N33: =SUM(N23:N32) -> 10048315
A35: EBITDA (reported) | B35: =B19-B33 -> 813342 | C35: =C19-C33 -> 637139 | D35: =D19-D33 -> 562348 | E35: =E19-E33 -> 327208 | F35: =F19-F33 -> 375593 | G35: =G19-G33 -> 491341 | H35: =H19-H33 -> 708639 | I35: =I19-I33 -> 840545 | ... N35: =N19-N33 -> 7503003
A36: EBITDA Margin % | B36: =IF(B9=0,0,B35/B9) -> 0.17734482 | C36: =IF(C9=0,0,C35/C9) -> 0.15672296 | D36: =IF(D9=0,0,D35/D9) -> 0.14606836 | E36: =IF(E9=0,0,E35/E9) -> 0.095968737 | F36: =IF(F9=0,0,F35/F9) -> 0.10553768 | G36: =IF(G9=0,0,G35/G9) -> 0.12091431 | H36: =IF(H9=0,0,H35/H9) -> 0.1538587 | I36: =IF(I9=0,0,I35/I9) -> 0.167425 | ... N36: =IF(N9=0,0,N35/N9) -> 0.13862271
A38: Below EBITDA
A39: Depreciation & Amortization | B39: 95000 | C39: 95000 | D39: 95000 | E39: 95000 | F39: 95000 | G39: 95000 | H39: 95000 | I39: 95000 | J39: 95000 | K39: 95000 | L39: 95000 | M39: 95000 | N39: =SUM(B39:M39) -> 1140000
A40: Interest Expense | B40: 340000 | C40: 340000 | D40: 340000 | E40: 340000 | F40: 340000 | G40: 340000 | H40: 340000 | I40: 340000 | J40: 425000 | K40: 425000 | L40: 425000 | M40: 425000 | N40: =SUM(B40:M40) -> 4420000
A41: Pre-tax Income | B41: =B35-SUM(B39:B40) -> 378342 | C41: =C35-SUM(C39:C40) -> 202139 | D41: =D35-SUM(D39:D40) -> 127348 | E41: =E35-SUM(E39:E40) -> -107792 | F41: =F35-SUM(F39:F40) -> -59407 | G41: =G35-SUM(G39:G40) -> 56341 | H41: =H35-SUM(H39:H40) -> 273639 | I41: =I35-SUM(I39:I40) -> 405545 | ... N41: =N35-SUM(N39:N40) -> 1943003

Sheet Adj EBITDA Bridge
A1: SYNTHETIC / ILLUSTRATIVE DATA. Fictional company. Not based on any real business. For demo and testing only.
A2: Platform A: Reported to Adjusted EBITDA, trailing twelve months ($)
A4: Item | B4: Oct-25 | C4: Nov-25 | D4: Dec-25 | E4: Jan-26 | F4: Feb-26 | G4: Mar-26 | H4: Apr-26 | I4: May-26 | J4: Jun-26 | K4: Jul-26 | L4: Aug-26 | M4: Sep-26 | N4: LTM | O4: Management description
A5: EBITDA (reported) | B5: ='P&L Trend'!B35 -> 813342 | C5: ='P&L Trend'!C35 -> 637139 | D5: ='P&L Trend'!D35 -> 562348 | E5: ='P&L Trend'!E35 -> 327208 | F5: ='P&L Trend'!F35 -> 375593 | G5: ='P&L Trend'!G35 -> 491341 | H5: ='P&L Trend'!H35 -> 708639 | I5: ='P&L Trend'!I35 -> 840545 | ... M5: ='P&L Trend'!M35 -> 460962 | N5: =SUM(B5:M5) -> 7503003
A6: + Sponsor monitoring fee | B6: 62500 | C6: 62500 | D6: 62500 | E6: 62500 | F6: 62500 | G6: 62500 | H6: 62500 | I6: 62500 | J6: 62500 | K6: 62500 | L6: 62500 | M6: 62500 | N6: =SUM(B6:M6) -> 750000 | O6: Contractual fee to sponsor; non-operating
A7: + Transaction costs | B7: 0 | C7: 0 | D7: 0 | E7: 0 | F7: 0 | G7: 0 | H7: 0 | I7: 0 | J7: 60000 | K7: 0 | L7: 0 | M7: 140000 | N7: =SUM(B7:M7) -> 200000 | O7: Jun: Add-on B closing. Sep: Project Falcon diligence
A8: + Integration costs | B8: 0 | C8: 0 | D8: 0 | E8: 0 | F8: 0 | G8: 0 | H8: 0 | I8: 0 | J8: 55000 | K8: 55000 | L8: 55000 | M8: 55000 | N8: =SUM(B8:M8) -> 220000 | O8: One-time costs to integrate Add-on B
A9: + Severance | B9: 0 | C9: 0 | D9: 0 | E9: 0 | F9: 0 | G9: 45000 | H9: 0 | I9: 0 | J9: 0 | K9: 0 | L9: 0 | M9: 0 | N9: =SUM(B9:M9) -> 45000 | O9: Regional manager departure
A10: + Non-recurring recruiting | B10: 0 | C10: 0 | D10: 0 | E10: 0 | F10: 0 | G10: 0 | H10: 0 | I10: 0 | J10: 0 | K10: 0 | L10: 30507 | M10: 32303 | N10: =SUM(B10:M10) -> 62810 | O10: Season staffing push, not expected to recur
A11: Adjusted EBITDA | B11: =SUM(B5:B10) -> 875842 | C11: =SUM(C5:C10) -> 699639 | D11: =SUM(D5:D10) -> 624848 | E11: =SUM(E5:E10) -> 389708 | F11: =SUM(F5:F10) -> 438093 | G11: =SUM(G5:G10) -> 598841 | H11: =SUM(H5:H10) -> 771139 | I11: =SUM(I5:I10) -> 903045 | ... M11: =SUM(M5:M10) -> 750765 | N11: =SUM(B11:M11) -> 8780813

Sheet Balance Sheet
A1: SYNTHETIC / ILLUSTRATIVE DATA. Fictional company. Not based on any real business. For demo and testing only.
A2: Platform A: Balance Sheet ($)
A4: Line item | B4: Sep-26 | C4: Aug-26 | D4: Dec-25
A5: Assets
A6: Cash | B6: 1920000 | C6: 2310000 | D6: 3050000
A7: Accounts Receivable, net | B7: 9240000 | C7: 8410000 | D7: 6020000
A8: Unbilled Receivables | B8: 410000 | C8: 365000 | D8: 240000
A9: Prepaid Expenses | B9: 285000 | C9: 300000 | D9: 260000
A10: Property & Equipment, net | B10: 1150000 | C10: 1170000 | D10: 1220000
A11: Goodwill & Intangibles | B11: 72400000 | C11: 72440000 | D11: 58700000
A12: Total Assets | B12: =SUM(B6:B11) -> 85405000 | C12: =SUM(C6:C11) -> 84995000 | D12: =SUM(D6:D11) -> 69490000
A14: Liabilities
A15: Accounts Payable | B15: 1480000 | C15: 1390000 | D15: 1110000
A16: Accrued Payroll | B16: 2140000 | C16: 1980000 | D16: 1310000
A17: Accrued Expenses | B17: 690000 | C17: 640000 | D17: 520000
A18: Revolver | B18: 4000000 | C18: 2500000 | D18: 0
A19: Term Loan (incl. current portion) | B19: 52500000 | C19: 52625000 | D19: 45000000
A20: Total Liabilities | B20: =SUM(B15:B19) -> 60810000 | C20: =SUM(C15:C19) -> 59135000 | D20: =SUM(D15:D19) -> 47940000
A21: Total Equity | B21: 24595000 | C21: 25860000 | D21: 21550000
A22: Check (should be zero) | B22: =B12-B20-B21 -> 0 | C22: =C12-C20-C21 -> 0 | D22: =D12-D20-D21 -> 0

Sheet AR Aging
A1: SYNTHETIC / ILLUSTRATIVE DATA. Fictional company. Not based on any real business. For demo and testing only.
A2: Platform A: AR Aging as of September 30, 2026 ($)
A4: Customer | B4: Current | C4: 31-60 | D4: 61-90 | E4: 90+ | F4: Total | G4: % of Total
A5: Venue 01 (stadium) | B5: 1120000 | C5: 640000 | D5: 280000 | E5: 310000 | F5: =SUM(B5:E5) -> 2350000 | G5: =IF($F$17=0,0,F5/$F$17) -> 0.25566293
A6: Venue 02 (arena) | B6: 870000 | C6: 300000 | D6: 60000 | E6: 0 | F6: =SUM(B6:E6) -> 1230000 | G6: =IF($F$17=0,0,F6/$F$17) -> 0.13381507
A7: Venue 03 (convention center) | B7: 760000 | C7: 210000 | D7: 40000 | E7: 12000 | F7: =SUM(B7:E7) -> 1022000 | G7: =IF($F$17=0,0,F7/$F$17) -> 0.11118618
A8: Venue 04 (amphitheater) | B8: 540000 | C8: 190000 | D8: 25000 | E8: 0 | F8: =SUM(B8:E8) -> 755000 | G8: =IF($F$17=0,0,F8/$F$17) -> 0.082138517
A9: Venue 05 (stadium) | B9: 610000 | C9: 120000 | D9: 0 | E9: 0 | F9: =SUM(B9:E9) -> 730000 | G9: =IF($F$17=0,0,F9/$F$17) -> 0.079418699
A10: Venue 06 (fairgrounds) | B10: 330000 | C10: 160000 | D10: 70000 | E10: 38000 | F10: =SUM(B10:E10) -> 598000 | G10: =IF($F$17=0,0,F10/$F$17) -> 0.065058057
A11: Venue 07 (arena) | B11: 420000 | C11: 95000 | D11: 0 | E11: 0 | F11: =SUM(B11:E11) -> 515000 | G11: =IF($F$17=0,0,F11/$F$17) -> 0.05602826
A12: Venue 08 (convention center) | B12: 390000 | C12: 70000 | D12: 15000 | E12: 0 | F12: =SUM(B12:E12) -> 475000 | G12: =IF($F$17=0,0,F12/$F$17) -> 0.05167655
A13: Venue 09 (festival promoter) | B13: 180000 | C13: 140000 | D13: 95000 | E13: 64000 | F13: =SUM(B13:E13) -> 479000 | G13: =IF($F$17=0,0,F13/$F$17) -> 0.052111721
A14: Venue 10 (university athletics) | B14: 300000 | C14: 60000 | D14: 0 | E14: 0 | F14: =SUM(B14:E14) -> 360000 | G14: =IF($F$17=0,0,F14/$F$17) -> 0.039165386
A15: Patrol accounts (commercial) | B15: 520000 | C15: 110000 | D15: 20000 | E15: 9000 | F15: =SUM(B15:E15) -> 659000 | G15: =IF($F$17=0,0,F15/$F$17) -> 0.071694414
A16: All other customers | B16: 13153 | C16: 3758 | D16: 1315 | E16: 564 | F16: =SUM(B16:E16) -> 18790 | G16: =IF($F$17=0,0,F16/$F$17) -> 0.0020442155
A17: Total | B17: =SUM(B5:B16) -> 6053153 | C17: =SUM(C5:C16) -> 2098758 | D17: =SUM(D5:D16) -> 606315 | E17: =SUM(E5:E16) -> 433564 | F17: =SUM(F5:F16) -> 9191790 | G17: =IF($F$17=0,0,F17/$F$17) -> 1
A18: % of total | B18: =IF($F$17=0,0,B17/$F$17) -> 0.65853909 | C18: =IF($F$17=0,0,C17/$F$17) -> 0.22832963 | D18: =IF($F$17=0,0,D17/$F$17) -> 0.065962669 | E18: =IF($F$17=0,0,E17/$F$17) -> 0.047168615

Sheet Operating KPIs
A1: SYNTHETIC / ILLUSTRATIVE DATA. Fictional company. Not based on any real business. For demo and testing only.
A2: Platform A: Operating KPIs, Event Staffing segment only (patrol excluded)
A4: KPI | B4: Oct-25 | C4: Nov-25 | D4: Dec-25 | E4: Jan-26 | F4: Feb-26 | G4: Mar-26 | H4: Apr-26 | I4: May-26 | J4: Jun-26 | K4: Jul-26 | L4: Aug-26 | M4: Sep-26 | N4: Definition
A5: Events worked | B5: 375 | C5: 326 | D5: 306 | E5: 253 | F5: 267 | G5: 313 | H5: 363 | I5: 403 | J5: 421 | K5: 427 | L5: 432 | M5: 435 | N5: Distinct events with at least one shift
A6: Shifts requested | B6: 14430 | C6: 12548 | D6: 11757 | E6: 9743 | F6: 10279 | G6: 12044 | H6: 13974 | I6: 15492 | J6: 16185 | K6: 16532 | L6: 17057 | M6: 17525 | N6: Shifts ordered by clients
A7: Shifts filled | B7: 14069 | C7: 12234 | D7: 11463 | E7: 9499 | F7: 10022 | G7: 11743 | H7: 13625 | I7: 15105 | J7: 15780 | K7: 16003 | L7: 16204 | M7: 16316 | N7: Shifts with a checked-in worker
A8: Fill rate | B8: =IF(B6=0,0,B7/B6) -> 0.97498267 | C8: =IF(C6=0,0,C7/C6) -> 0.97497609 | D8: =IF(D6=0,0,D7/D6) -> 0.97499362 | E8: =IF(E6=0,0,E7/E6) -> 0.97495638 | F8: =IF(F6=0,0,F7/F6) -> 0.97499757 | G8: =IF(G6=0,0,G7/G6) -> 0.9750083 | H8: =IF(H6=0,0,H7/H6) -> 0.97502505 | I8: =IF(I6=0,0,I7/I6) -> 0.97501936 | ... M8: =IF(M6=0,0,M7/M6) -> 0.93101284 | N8: Shifts filled / shifts requested
A9: No-show rate | B9: 0.031 | C9: 0.031 | D9: 0.031 | E9: 0.031 | F9: 0.031 | G9: 0.031 | H9: 0.031 | I9: 0.031 | J9: 0.031 | K9: 0.031 | L9: 0.052 | M9: 0.064 | N9: Scheduled workers who did not check in
A10: Billed hours | B10: 106928 | C10: 92979 | D10: 87122 | E10: 72195 | F10: 76169 | G10: 89248 | H10: 103549 | I10: 114798 | J10: 119928 | K10: 121625 | L10: 123152 | M10: 124002 | N10: Hours invoiced to clients
A11: Paid hours | B11: 110671 | C11: 96233 | D11: 90171 | E11: 74722 | F11: 78835 | G11: 92372 | H11: 107173 | I11: 118816 | J11: 124126 | K11: 125882 | L11: 122221 | M11: 131690 | N11: Hours paid through payroll
A12: Paid / billed ratio | B12: =IF(B10=0,0,B11/B10) -> 1.0350049 | C12: =IF(C10=0,0,C11/C10) -> 1.0349971 | D12: =IF(D10=0,0,D11/D10) -> 1.0349969 | E12: =IF(E10=0,0,E11/E10) -> 1.0350024 | F12: =IF(F10=0,0,F11/F10) -> 1.0350011 | G12: =IF(G10=0,0,G11/G10) -> 1.0350036 | H12: =IF(H10=0,0,H11/H10) -> 1.0349979 | I12: =IF(I10=0,0,I11/I10) -> 1.0350006 | ... M12: =IF(M10=0,0,M11/M10) -> 1.061999 | N12: Paid hours / billed hours; >1 means unbillable time
A13: Average bill rate ($/hr) | B13: 35.5 | C13: 35.5 | D13: 35.5 | E13: 36.4 | F13: 36.4 | G13: 36.4 | H13: 36.4 | I13: 36.4 | J13: 36.4 | K13: 36.4 | L13: 36.4 | M13: 36.4 | N13: Blended rate charged to clients
A14: Average pay rate ($/hr) | B14: 18.6 | C14: 18.6 | D14: 18.6 | E14: 19.75 | F14: 19.75 | G14: 19.75 | H14: 19.75 | I14: 19.75 | J14: 19.75 | K14: 19.75 | L14: 19.75 | M14: 19.75 | N14: Blended base wage
A15: Spread ($/hr) | B15: =B13-B14 -> 16.9 | C15: =C13-C14 -> 16.9 | D15: =D13-D14 -> 16.9 | E15: =E13-E14 -> 16.65 | F15: =F13-F14 -> 16.65 | G15: =G13-G14 -> 16.65 | H15: =H13-H14 -> 16.65 | I15: =I13-I14 -> 16.65 | ... M15: =M13-M14 -> 16.65 | N15: Bill rate minus pay rate, before burden
A16: Overtime % of paid hours | B16: 0.042 | C16: 0.042 | D16: 0.042 | E16: 0.042 | F16: 0.042 | G16: 0.042 | H16: 0.042 | I16: 0.042 | J16: 0.042 | K16: 0.042 | L16: 0.071 | M16: 0.088 | N16: OT hours / paid hours
A17: Active workforce (headcount) | B17: 2110 | C17: 2020 | D17: 1990 | E17: 1870 | F17: 1882 | G17: 1960 | H17: 2050 | I17: 2110 | J17: 2140 | K17: 2140 | L17: 2122 | M17: 2170 | N17: Workers with a shift in the month
A18: New hires | B18: 190 | C18: 182 | D18: 179 | E18: 168 | F18: 169 | G18: 176 | H18: 184 | I18: 190 | J18: 193 | K18: 193 | L18: 340 | M18: 347 | N18: Workers onboarded
A19: Terminations | B19: 169 | C19: 162 | D19: 159 | E19: 150 | F19: 151 | G19: 157 | H19: 164 | I19: 169 | J19: 171 | K19: 171 | L19: 233 | M19: 239 | N19: Workers separated
A20: Annualized turnover | B20: =IF(B17=0,0,B19*12/B17) -> 0.96113744 | C20: =IF(C17=0,0,C19*12/C17) -> 0.96237624 | D20: =IF(D17=0,0,D19*12/D17) -> 0.95879397 | E20: =IF(E17=0,0,E19*12/E17) -> 0.96256684 | F20: =IF(F17=0,0,F19*12/F17) -> 0.96280553 | G20: =IF(G17=0,0,G19*12/G17) -> 0.96122449 | H20: =IF(H17=0,0,H19*12/H17) -> 0.96 | I20: =IF(I17=0,0,I19*12/I17) -> 0.96113744 | ... M20: =IF(M17=0,0,M19*12/M17) -> 1.321659 | N20: Terminations x 12 / active workforce
A22: Reconciliation to P&L
A23: Implied staffing revenue (billed hrs x bill rate) | B23: =B10*B13 -> 3795944 | C23: =C10*C13 -> 3300754.5 | D23: =D10*D13 -> 3092831 | E23: =E10*E13 -> 2627898 | F23: =F10*F13 -> 2772551.6 | G23: =G10*G13 -> 3248627.2 | H23: =H10*H13 -> 3769183.6 | I23: =I10*I13 -> 4178647.2 | ... M23: =M10*M13 -> 4513672.8 | N23: KPI-derived revenue
A24: Reported Event Staffing Revenue | B24: ='P&L Trend'!B6 -> 3795946 | C24: ='P&L Trend'!C6 -> 3300749 | D24: ='P&L Trend'!D6 -> 3092832 | E24: ='P&L Trend'!E6 -> 2627915 | F24: ='P&L Trend'!F6 -> 2772557 | G24: ='P&L Trend'!G6 -> 3248641 | H24: ='P&L Trend'!H6 -> 3769179 | I24: ='P&L Trend'!I6 -> 4178653 | ... M24: ='P&L Trend'!M6 -> 4513673 | N24: From P&L Trend
A25: Difference % | B25: =IF(B24=0,0,B23/B24-1) -> -5.2687788e-07 | C25: =IF(C24=0,0,C23/C24-1) -> 1.6662885e-06 | D25: =IF(D24=0,0,D23/D24-1) -> -3.2332826e-07 | E25: =IF(E24=0,0,E23/E24-1) -> -6.4690068e-06 | F25: =IF(F24=0,0,F23/F24-1) -> -1.9476606e-06 | G25: =IF(G24=0,0,G23/G24-1) -> -4.2479301e-06 | H25: =IF(H24=0,0,H23/H24-1) -> 1.2204249e-06 | I25: =IF(I24=0,0,I23/I24-1) -> -1.3880071e-06 | ... M25: =IF(M24=0,0,M23/M24-1) -> -4.4309812e-08 | N25: Should be within +/- 1%

Sheet Revenue by Customer
A1: SYNTHETIC / ILLUSTRATIVE DATA. Fictional company. Not based on any real business. For demo and testing only.
A2: Platform A: LTM revenue by customer (Oct-25 to Sep-26)
A4: Customer | B4: LTM Revenue ($) | C4: % of Total | D4: Contract type | E4: Contract expiry | F4: Rate escalator | G4: Notes
A5: Venue 01 (stadium) | B5: 11474575 | C5: =IF($B$17=0,0,B5/$B$17) -> 0.212 | D5: Multi-year rate card | E5: Mar-2027 | F5: 3% annual | G5: Renewal RFP expected Q1 2027
A6: Venue 02 (arena) | B6: 6386792 | C6: =IF($B$17=0,0,B6/$B$17) -> 0.118 | D6: Multi-year rate card | E6: Dec-2028 | F6: CPI
A7: Venue 03 (convention center) | B7: 5087783 | C7: =IF($B$17=0,0,B7/$B$17) -> 0.093999995 | D7: Annual | E7: Jun-2027 | F7: None | G7: Added Jul-2026
A8: Venue 04 (amphitheater) | B8: 3842900 | C8: =IF($B$17=0,0,B8/$B$17) -> 0.070999998 | D8: Seasonal | E8: Oct-2026 | F8: None | G8: Season contract ends this month
A9: Venue 05 (stadium) | B9: 3572273 | C9: =IF($B$17=0,0,B9/$B$17) -> 0.065999993 | D9: Multi-year rate card | E9: Feb-2029 | F9: 3% annual
A10: Venue 06 (fairgrounds) | B10: 2435641 | C10: =IF($B$17=0,0,B10/$B$17) -> 0.045000001 | D10: Event-by-event | E10: n/a | F10: None
A11: Venue 07 (arena) | B11: 2327390 | C11: =IF($B$17=0,0,B11/$B$17) -> 0.042999996 | D11: Multi-year rate card | E11: Aug-2027 | F11: 2.5% annual
A12: Venue 08 (convention center) | B12: 2056763 | C12: =IF($B$17=0,0,B12/$B$17) -> 0.037999992 | D12: Annual | E12: Jan-2027 | F12: None | G12: Added Jul-2026
A13: Venue 09 (festival promoter) | B13: 1677886 | C13: =IF($B$17=0,0,B13/$B$17) -> 0.031 | D13: Event-by-event | E13: n/a | F13: None
A14: Venue 10 (university athletics) | B14: 1569635 | C14: =IF($B$17=0,0,B14/$B$17) -> 0.028999995 | D14: Multi-year rate card | E14: Jun-2028 | F14: CPI
A15: Patrol accounts (commercial) | B15: 7415173 | C15: =IF($B$17=0,0,B15/$B$17) -> 0.13699999 | D15: Monthly service agreements | E15: Various | F15: Various
A16: All other customers | B16: ='P&L Trend'!N9-SUM(B5:B15) -> 6278543 | C16: =IF($B$17=0,0,B16/$B$17) -> 0.11600004
A17: Total | B17: =SUM(B5:B16) -> 54125354 | C17: =IF($B$17=0,0,B17/$B$17) -> 1

Sheet Covenant
A1: SYNTHETIC / ILLUSTRATIVE DATA. Fictional company. Not based on any real business. For demo and testing only.
A2: Platform A: Covenant Compliance Certificate, quarter ended September 30, 2026
A4: Item | B4: Value | C4: Source / note
A5: LTM Adjusted EBITDA (Platform A) | B5: ='Adj EBITDA Bridge'!N11 -> 8780813 | C5: From Adjusted EBITDA bridge
A6: Pro forma Add-on B EBITDA, pre-acquisition period (Oct-25 to May-26) | B6: 1240000 | C6: Per sell-side QoE
A7: Add-on B EBITDA, post-acquisition (Jun-26 to Sep-26) | B7: 610000 | C7: Per Add-on B management accounts
A8: Run-rate cost synergies | B8: 2100000 | C8: Identified in diligence
A9: Covenant EBITDA (as reported) | B9: =SUM(B5:B8) -> 12730813
A11: Term loan | B11: ='Balance Sheet'!B19 -> 52500000
A12: Revolver | B12: ='Balance Sheet'!B18 -> 4000000
A13: Less: cash | B13: =-'Balance Sheet'!B6 -> -1920000
A14: Net debt | B14: =SUM(B11:B13) -> 54580000
A16: Net leverage (as reported) | B16: =IF(B9=0,0,B14/B9) -> 4.287236
A17: Maximum permitted | B17: 4.75 | C17: Steps down to 4.50x at Mar-27 test date
A18: Headroom | B18: =B17-B16 -> 0.46276398
A20: Credit agreement terms (excerpt)
A21: Synergy add-back cap, % of covenant EBITDA before synergies | B21: 0.15 | C21: Synergies must be realizable within 12 months
