Workbook

Sheet MP Letter
A1: TALLIS BROOK ACCOUNTING GROUP
A2: Managing Partner's Letter to the Sponsor, September 2026
A3: Synthetic test data. Fictional firm and clients; not based on any real business.
A5: Year to date, net fee revenue is up 70% over the prior year. That reflects strong organic demand across our offices and continued expansion of Client Accounting Services, which is now our fastest-growing service line, up 74% year to date.
A7: September was a heavy month for business and trust returns ahead of the September 15 extension deadline, and the teams delivered on time. Firmwide realization held above 90%, consistent with our historical range, and utilization remained healthy.
A9: Integration: Partner compensation has now been aligned with the platform model across all acquired practices, and Ashcombe's client transition following its founding partner's retirement in May is complete, with client retention firmwide remaining above 95%. Wexley joined on July 1 and is already operating on our tax and practice management systems.
A11: Redfern is adapting to our engagement and billing standards. Some fixed-fee engagements inherited at acquisition are running over budget, and we expect them to be repriced at renewal. We do not anticipate material write-downs beyond what has been recorded.
A13: Outlook: We are on track for full-year results in line with the acquisition model. Our pipeline includes two additional practices under letter of intent, and we expect to sign one before year-end.
A15: Managing Partner

Sheet Dashboard
A1: TALLIS BROOK ACCOUNTING GROUP
A2: Sponsor Dashboard, September 2026
A3: US dollars unless noted | Synthetic test data. Fictional firm and clients; not based on any real business.
A5: Metric | B5: Sep-26 | C5: Sep-25 | D5: YoY change | E5: YTD 2026 | F5: YTD 2025
A6: Net fee revenue | B6: ='Practice P&L'!G12 -> 3475418 | C6: ='Practice P&L'!H12 -> 1808746 | D6: =IF(C6=0,0,B6/C6-1) -> 0.92145166 | E6: ='Monthly Trend'!K12 -> 23171006 | F6: ='Monthly Trend'!M12 -> 13657612
A7: EBITDA (reported) | B7: ='Practice P&L'!G41 -> 684306 | C7: ='Practice P&L'!H41 -> 459265 | D7: =IF(C7=0,0,B7/C7-1) -> 0.4900025 | E7: ='Monthly Trend'!K40 -> 3916548 | F7: ='Monthly Trend'!M40 -> 3095415
A8: EBITDA margin | B8: =IF(B6=0,0,B7/B6) -> 0.19689891 | C8: =IF(C6=0,0,C7/C6) -> 0.25391348 | D8: =B8-C8 -> -0.057014579 | E8: =IF(E6=0,0,E7/E6) -> 0.16902797 | F8: =IF(F6=0,0,F7/F6) -> 0.22664394
A9: CAS revenue | B9: ='Practice P&L'!G9 -> 672031 | C9: ='Practice P&L'!H9 -> 348508 | D9: =IF(C9=0,0,B9/C9-1) -> 0.92830868 | E9: ='Monthly Trend'!K9 -> 5242495 | F9: ='Monthly Trend'!M9 -> 3009728
A10: LTM pro forma adjusted EBITDA | B10: ='Adjusted EBITDA'!B17 -> 7941214.7
A11: Total FTEs (excluding offshore) | B11: 184
A12: Annualized revenue per FTE (Q3 run-rate) | B12: =IF(B11=0,0,'WIP AR Realization'!F28*4/B11) -> 169674.02
A13: Firm realization (Sep) | B13: ='WIP AR Realization'!F9 -> 0.87952868
A14: Firm lockup days | B14: ='WIP AR Realization'!F31 -> 91.237081
A15: Gross client retention (LTM) | B15: ='Client Book'!F10 -> 0.93961606

Sheet Practice P&L
A1: TALLIS BROOK ACCOUNTING GROUP
A2: P&L by Practice, September 2026
A3: US dollars | Synthetic test data. Fictional firm and clients; not based on any real business.
B5: Tallis Brook (legacy) | C5: Ashcombe (acq. Nov-25) | D5: Redfern (acq. Mar-26) | E5: Wexley (acq. Jul-26) | F5: Corporate | G5: Consolidated Sep-26 | H5: Consolidated Sep-25 | I5: Budget Sep-26
A6: Fee revenue
A7: Tax - Individual | B7: 305831 | C7: 120600 | D7: 99773 | E7: 87328 | F7: 0 | G7: =SUM(B7:F7) -> 613532 | H7: 295074 | I7: 648000
A8: Tax - Business & Trust | B8: 786530 | C8: 245874 | D8: 273853 | E8: 222814 | F8: 0 | G8: =SUM(B8:F8) -> 1529071 | H8: 756600 | I8: 1615000
A9: Client Accounting Services (CAS) | B9: 392056 | C9: 101209 | D9: 65375 | E9: 113391 | F9: 0 | G9: =SUM(B9:F9) -> 672031 | H9: 348508 | I9: 703032
A10: Audit & Assurance (ASA fee) | B10: 308319 | C10: 50715 | D10: 69916 | E10: 43558 | F10: 0 | G10: =SUM(B10:F10) -> 472508 | H10: 295074 | I10: 487800
A11: Advisory & Other | B11: 116594 | C11: 22155 | D11: 33301 | E11: 16226 | F11: 0 | G11: =SUM(B11:F11) -> 188276 | H11: 113490 | I11: 198000
A12: Net Fee Revenue | B12: =SUM(B7:B11) -> 1909330 | C12: =SUM(C7:C11) -> 540553 | D12: =SUM(D7:D11) -> 542218 | E12: =SUM(E7:E11) -> 483317 | F12: =SUM(F7:F11) -> 0 | G12: =SUM(B12:F12) -> 3475418 | H12: =SUM(H7:H11) -> 1808746 | I12: =SUM(I7:I11) -> 3651832
A14: Professional compensation & direct costs
A15: Professional Staff Salaries | B15: 572799 | C15: 162166 | D15: 192487 | E15: 144995 | F15: 0 | G15: =SUM(B15:F15) -> 1072447 | H15: 542624 | I15: 1095550
A16: Partner & Principal Compensation | B16: 150000 | C16: 50000 | D16: 116667 | E16: 50000 | F16: 0 | G16: =SUM(B16:F16) -> 366667 | H16: 150000 | I16: 325000
A17: Bonus Accrual | B17: 57280 | C17: 16217 | D17: 16267 | E17: 14500 | F17: 0 | G17: =SUM(B17:F17) -> 104264 | H17: 54262 | I17: 109555
A18: Payroll Taxes & Benefits | B18: 130104 | C18: 38190 | D18: 55648 | E18: 35099 | F18: 0 | G18: =SUM(B18:F18) -> 259041 | H18: 124672 | I18: 255699
A19: Offshore & Contract Staff | B19: 57280 | C19: 5406 | D19: 5422 | E19: 4833 | F19: 0 | G19: =SUM(B19:F19) -> 72941 | H19: 54262 | I19: 74547
A20: Total Direct Costs | B20: =SUM(B15:B19) -> 967463 | C20: =SUM(C15:C19) -> 271979 | D20: =SUM(D15:D19) -> 386491 | E20: =SUM(E15:E19) -> 249427 | F20: =SUM(F15:F19) -> 0 | G20: =SUM(B20:F20) -> 1875360 | H20: =SUM(H15:H19) -> 925820 | I20: =SUM(I15:I19) -> 1860351
A21: Practice Margin | B21: =B12-B20 -> 941867 | C21: =C12-C20 -> 268574 | D21: =D12-D20 -> 155727 | E21: =E12-E20 -> 233890 | F21: =F12-F20 -> 0 | G21: =SUM(B21:F21) -> 1600058 | H21: =H12-H20 -> 882926 | I21: =I12-I20 -> 1791481
A22: Practice margin % | B22: =IF(B12=0,0,B21/B12) -> 0.49329713 | C22: =IF(C12=0,0,C21/C12) -> 0.49685045 | D22: =IF(D12=0,0,D21/D12) -> 0.28720367 | E22: =IF(E12=0,0,E21/E12) -> 0.4839267 | G22: =IF(G12=0,0,G21/G12) -> 0.46039297 | H22: =IF(H12=0,0,H21/H12) -> 0.48814261 | I22: =IF(I12=0,0,I21/I12) -> 0.49057049
A24: Office operating expenses
A25: Occupancy | B25: 95466 | C25: 27028 | D25: 27111 | E25: 24166 | F25: 0 | G25: =SUM(B25:F25) -> 173771 | H25: 90437 | I25: 182592
A26: Technology & Tax Software | B26: 76373 | C26: 21622 | D26: 27111 | E26: 19333 | F26: 0 | G26: =SUM(B26:F26) -> 144439 | H26: 72350 | I26: 152482
A27: Admin & Support Salaries | B27: 105013 | C27: 29730 | D27: 29822 | E27: 26582 | F27: 0 | G27: =SUM(B27:F27) -> 191147 | H27: 99481 | I27: 200851
A28: Professional Liability Insurance | B28: 22912 | C28: 6487 | D28: 6507 | E28: 5800 | F28: 0 | G28: =SUM(B28:F28) -> 41706 | H28: 21705 | I28: 43822
A29: CPE, Licensing & Dues | B29: 15275 | C29: 4324 | D29: 4338 | E29: 3867 | F29: 0 | G29: =SUM(B29:F29) -> 27804 | H29: 14470 | I29: 29214
A30: Marketing & Business Development | B30: 19093 | C30: 5406 | D30: 5422 | E30: 4833 | F30: 0 | G30: =SUM(B30:F30) -> 34754 | H30: 18087 | I30: 36518
A31: Travel & Other | B31: 28640 | C31: 8108 | D31: 8133 | E31: 7250 | F31: 0 | G31: =SUM(B31:F31) -> 52131 | H31: 27131 | I31: 54777
A32: Total Office Opex | B32: =SUM(B25:B31) -> 362772 | C32: =SUM(C25:C31) -> 102705 | D32: =SUM(D25:D31) -> 108444 | E32: =SUM(E25:E31) -> 91831 | F32: =SUM(F25:F31) -> 0 | G32: =SUM(B32:F32) -> 665752 | H32: =SUM(H25:H31) -> 343661 | I32: =SUM(I25:I31) -> 700256
A34: Corporate
A35: Corporate Team (Finance, HR, IT) | B35: 0 | C35: 0 | D35: 0 | E35: 0 | F35: 110000 | G35: =SUM(B35:F35) -> 110000 | H35: 45000 | I35: 110000
A36: Integration Costs | B36: 0 | C36: 0 | D36: 0 | E36: 0 | F36: 45000 | G36: =SUM(B36:F36) -> 45000 | H36: 0 | I36: 0
A37: Transaction Costs | B37: 0 | C37: 0 | D37: 0 | E37: 0 | F37: 60000 | G37: =SUM(B37:F37) -> 60000 | H37: 0 | I37: 0
A38: Sponsor Monitoring Fee | B38: 0 | C38: 0 | D38: 0 | E38: 0 | F38: 35000 | G38: =SUM(B38:F38) -> 35000 | H38: 35000 | I38: 35000
A39: Total Corporate | B39: =SUM(B35:B38) -> 0 | C39: =SUM(C35:C38) -> 0 | D39: =SUM(D35:D38) -> 0 | E39: =SUM(E35:E38) -> 0 | F39: =SUM(F35:F38) -> 250000 | G39: =SUM(B39:F39) -> 250000 | H39: =SUM(H35:H38) -> 80000 | I39: =SUM(I35:I38) -> 145000
A41: EBITDA (reported) | B41: =B21-B32-B39 -> 579095 | C41: =C21-C32-C39 -> 165869 | D41: =D21-D32-D39 -> 47283 | E41: =E21-E32-E39 -> 142059 | F41: =F21-F32-F39 -> -250000 | G41: =SUM(B41:F41) -> 684306 | H41: =H21-H32-H39 -> 459265 | I41: =I21-I32-I39 -> 946225
A42: EBITDA margin % | B42: =IF(B12=0,0,B41/B12) -> 0.30329749 | C42: =IF(C12=0,0,C41/C12) -> 0.30685058 | D42: =IF(D12=0,0,D41/D12) -> 0.087202933 | E42: =IF(E12=0,0,E41/E12) -> 0.29392511 | G42: =IF(G12=0,0,G41/G12) -> 0.19689891 | H42: =IF(H12=0,0,H41/H12) -> 0.25391348 | I42: =IF(I12=0,0,I41/I12) -> 0.25910967
A44: Note: Sep-25 reflects Tallis Brook (legacy) only; acquired practices are included from their acquisition dates.

Sheet Monthly Trend
A1: TALLIS BROOK ACCOUNTING GROUP
A2: Consolidated Monthly P&L, January to September 2026
A3: US dollars | Synthetic test data. Fictional firm and clients; not based on any real business.
A5: Line | B5: Jan-26 | C5: Feb-26 | D5: Mar-26 | E5: Apr-26 | F5: May-26 | G5: Jun-26 | H5: Jul-26 | I5: Aug-26 | J5: Sep-26 | K5: YTD 2026 | L5: YTD Budget | M5: YTD 2025
A6: Fee revenue
A7: Tax - Individual | B7: 298153 | C7: 594568 | D7: 1220992 | E7: 1605967 | F7: 246436 | G7: 181751 | H7: 206080 | I7: 271275 | J7: 613532 | K7: =SUM(B7:J7) -> 5238754 | L7: 5348400 | M7: 2852382
A8: Tax - Business & Trust | B8: 371848 | C8: 698282 | D8: 1314485 | E8: 680227 | F8: 411227 | G8: 403437 | H8: 464924 | I8: 617907 | J8: 1529071 | K8: =SUM(B8:J8) -> 6491408 | L8: 6663050 | M8: 3593850
A9: Client Accounting Services (CAS) | B9: 478557 | C9: 480975 | D9: 565209 | E9: 564212 | F9: 567727 | G9: 564195 | H9: 676600 | I9: 672989 | J9: 672031 | K9: =SUM(B9:J9) -> 5242495 | L9: 5355144 | M9: 3009728
A10: Audit & Assurance (ASA fee) | B10: 365022 | C10: 529122 | D10: 731202 | E10: 679115 | F10: 436637 | G10: 379424 | H10: 519653 | I10: 523049 | J10: 472508 | K10: =SUM(B10:J10) -> 4635732 | L10: 4730800 | M10: 3180242
A11: Advisory & Other | B11: 141751 | C11: 141712 | D11: 179615 | E11: 180947 | F11: 177666 | G11: 175540 | H11: 188466 | I11: 188644 | J11: 188276 | K11: =SUM(B11:J11) -> 1562617 | L11: 1608000 | M11: 1021410
A12: Net Fee Revenue | B12: =SUM(B7:B11) -> 1655331 | C12: =SUM(C7:C11) -> 2444659 | D12: =SUM(D7:D11) -> 4011503 | E12: =SUM(E7:E11) -> 3710468 | F12: =SUM(F7:F11) -> 1839693 | G12: =SUM(G7:G11) -> 1704347 | H12: =SUM(H7:H11) -> 2055723 | I12: =SUM(I7:I11) -> 2273864 | J12: =SUM(J7:J11) -> 3475418 | K12: =SUM(B12:J12) -> 23171006 | L12: =SUM(L7:L11) -> 23705394 | M12: =SUM(M7:M11) -> 13657612
A14: Professional compensation & direct costs
A15: Professional Staff Salaries | B15: 496599 | C15: 733398 | D15: 1246783 | E15: 1151333 | F15: 569320 | G15: 527352 | H15: 633305 | I15: 700439 | J15: 1072447 | K15: =SUM(B15:J15) -> 7130976 | L15: 7111618 | M15: 4097284
A16: Partner & Principal Compensation | B16: 200000 | C16: 200000 | D16: 316667 | E16: 316667 | F16: 316667 | G16: 316667 | H16: 366667 | I16: 366667 | J16: 366667 | K16: =SUM(B16:J16) -> 2766669 | L16: 2475000 | M16: 1350000
A17: Bonus Accrual | B17: 49660 | C17: 73340 | D17: 120345 | E17: 111314 | F17: 55191 | G17: 51130 | H17: 61672 | I17: 68216 | J17: 104264 | K17: =SUM(B17:J17) -> 695132 | L17: 711162 | M17: 409728
A18: Payroll Taxes & Benefits | B18: 125388 | C18: 168011 | D18: 281421 | E18: 264240 | F18: 159478 | G18: 151924 | H18: 179995 | I18: 192079 | J18: 259041 | K18: =SUM(B18:J18) -> 1781577 | L18: 1725590 | M18: 980511
A19: Offshore & Contract Staff | B19: 41757 | C19: 61287 | D19: 88227 | E19: 81786 | F19: 41843 | G19: 39235 | H19: 44091 | I19: 48774 | J19: 72941 | K19: =SUM(B19:J19) -> 519941 | L19: 525000 | M19: 409728
A20: Total Direct Costs | B20: =SUM(B15:B19) -> 913404 | C20: =SUM(C15:C19) -> 1236036 | D20: =SUM(D15:D19) -> 2053443 | E20: =SUM(E15:E19) -> 1925340 | F20: =SUM(F15:F19) -> 1142499 | G20: =SUM(G15:G19) -> 1086308 | H20: =SUM(H15:H19) -> 1285730 | I20: =SUM(I15:I19) -> 1376175 | J20: =SUM(J15:J19) -> 1875360 | K20: =SUM(B20:J20) -> 12894295 | L20: =SUM(L15:L19) -> 12548370 | M20: =SUM(M15:M19) -> 7247251
A21: Practice Margin | B21: =B12-B20 -> 741927 | C21: =C12-C20 -> 1208623 | D21: =D12-D20 -> 1958060 | E21: =E12-E20 -> 1785128 | F21: =F12-F20 -> 697194 | G21: =G12-G20 -> 618039 | H21: =H12-H20 -> 769993 | I21: =I12-I20 -> 897689 | ... M21: =M12-M20 -> 6410361
A23: Office operating expenses
A24: Occupancy | B24: 82767 | C24: 122233 | D24: 200575 | E24: 185524 | F24: 91985 | G24: 85217 | H24: 102787 | I24: 113693 | J24: 173771 | K24: =SUM(B24:J24) -> 1158552 | L24: 1185269 | M24: 682880
A25: Technology & Tax Software | B25: 66213 | C25: 97786 | D25: 168339 | E25: 155363 | F25: 76753 | G25: 71092 | H25: 85244 | I25: 94278 | J25: 144439 | K25: =SUM(B25:J25) -> 959507 | L25: 984387 | M25: 546304
A26: Admin & Support Salaries | B26: 91043 | C26: 134456 | D26: 220632 | E26: 204076 | F26: 101183 | G26: 93739 | H26: 113064 | I26: 125063 | J26: 191147 | K26: =SUM(B26:J26) -> 1274403 | L26: 1303798 | M26: 751171
A27: Professional Liability Insurance | B27: 19864 | C27: 29336 | D27: 48138 | E27: 44526 | F27: 22076 | G27: 20451 | H27: 24669 | I27: 27287 | J27: 41706 | K27: =SUM(B27:J27) -> 278053 | L27: 284464 | M27: 163891
A28: CPE, Licensing & Dues | B28: 13242 | C28: 19557 | D28: 32092 | E28: 29684 | F28: 14718 | G28: 13635 | H28: 16446 | I28: 18191 | J28: 27804 | K28: =SUM(B28:J28) -> 185369 | L28: 189643 | M28: 109260
A29: Marketing & Business Development | B29: 16554 | C29: 24446 | D29: 40114 | E29: 37105 | F29: 18398 | G29: 17043 | H29: 20558 | I29: 22739 | J29: 34754 | K29: =SUM(B29:J29) -> 231711 | L29: 237052 | M29: 136575
A30: Travel & Other | B30: 24830 | C30: 36670 | D30: 60173 | E30: 55657 | F30: 27596 | G30: 25565 | H30: 30837 | I30: 34109 | J30: 52131 | K30: =SUM(B30:J30) -> 347568 | L30: 355580 | M30: 204865
A31: Total Office Opex | B31: =SUM(B24:B30) -> 314513 | C31: =SUM(C24:C30) -> 464484 | D31: =SUM(D24:D30) -> 770063 | E31: =SUM(E24:E30) -> 711935 | F31: =SUM(F24:F30) -> 352709 | G31: =SUM(G24:G30) -> 326742 | H31: =SUM(H24:H30) -> 393605 | I31: =SUM(I24:I30) -> 435360 | J31: =SUM(J24:J30) -> 665752 | K31: =SUM(B31:J31) -> 4435163 | L31: =SUM(L24:L30) -> 4540193 | M31: =SUM(M24:M30) -> 2594946
A33: Corporate
A34: Corporate Team (Finance, HR, IT) | B34: 110000 | C34: 110000 | D34: 110000 | E34: 110000 | F34: 110000 | G34: 110000 | H34: 110000 | I34: 110000 | J34: 110000 | K34: =SUM(B34:J34) -> 990000 | L34: 990000 | M34: 405000
A35: Integration Costs | B35: 45000 | C35: 45000 | D35: 45000 | E35: 45000 | F35: 45000 | G35: 45000 | H35: 45000 | I35: 45000 | J35: 45000 | K35: =SUM(B35:J35) -> 405000 | L35: 0 | M35: 0
A36: Transaction Costs | B36: 0 | C36: 0 | D36: 85000 | E36: 0 | F36: 0 | G36: 0 | H36: 70000 | I36: 0 | J36: 60000 | K36: =SUM(B36:J36) -> 215000 | L36: 0 | M36: 0
A37: Sponsor Monitoring Fee | B37: 35000 | C37: 35000 | D37: 35000 | E37: 35000 | F37: 35000 | G37: 35000 | H37: 35000 | I37: 35000 | J37: 35000 | K37: =SUM(B37:J37) -> 315000 | L37: 315000 | M37: 315000
A38: Total Corporate | B38: =SUM(B34:B37) -> 190000 | C38: =SUM(C34:C37) -> 190000 | D38: =SUM(D34:D37) -> 275000 | E38: =SUM(E34:E37) -> 190000 | F38: =SUM(F34:F37) -> 190000 | G38: =SUM(G34:G37) -> 190000 | H38: =SUM(H34:H37) -> 260000 | I38: =SUM(I34:I37) -> 190000 | J38: =SUM(J34:J37) -> 250000 | K38: =SUM(B38:J38) -> 1925000 | L38: =SUM(L34:L37) -> 1305000 | M38: =SUM(M34:M37) -> 720000
A40: EBITDA (reported) | B40: =B21-B31-B38 -> 237414 | C40: =C21-C31-C38 -> 554139 | D40: =D21-D31-D38 -> 912997 | E40: =E21-E31-E38 -> 883193 | F40: =F21-F31-F38 -> 154485 | G40: =G21-G31-G38 -> 101297 | H40: =H21-H31-H38 -> 116388 | I40: =I21-I31-I38 -> 272329 | ... M40: =M21-M31-M38 -> 3095415
A41: EBITDA margin | B41: =IF(B12=0,0,B40/B12) -> 0.14342388 | C41: =IF(C12=0,0,C40/C12) -> 0.22667333 | D41: =IF(D12=0,0,D40/D12) -> 0.22759474 | E41: =IF(E12=0,0,E40/E12) -> 0.23802739 | F41: =IF(F12=0,0,F40/F12) -> 0.08397325 | G41: =IF(G12=0,0,G40/G12) -> 0.059434493 | H41: =IF(H12=0,0,H40/H12) -> 0.056616577 | I41: =IF(I12=0,0,I40/I12) -> 0.11976486 | ... M41: =IF(M12=0,0,M40/M12) -> 0.22664394

Sheet Adjusted EBITDA
A1: TALLIS BROOK ACCOUNTING GROUP
A2: LTM Pro Forma Adjusted EBITDA, Twelve Months Ended September 30, 2026
A3: US dollars | Synthetic test data. Fictional firm and clients; not based on any real business.
A5: Item | B5: Amount ($) | C5: Source / basis
A6: Reported EBITDA, Jan to Sep 2026 | B6: ='Monthly Trend'!K40 -> 3916548 | C6: Monthly Trend
A7: Reported EBITDA, Oct to Dec 2025 | B7: 1264000 | C7: 2025 management accounts (Tallis Brook; Ashcombe from Nov-25)
A8: LTM reported EBITDA | B8: =B6+B7 -> 5180548
A10: Pre-acquisition EBITDA: Ashcombe (Oct-25) | B10: 83000 | C10: Sell-side QoE
A11: Pre-acquisition EBITDA: Redfern (Oct-25 to Feb-26) | B11: 519000 | C11: Sell-side QoE
A12: Pre-acquisition EBITDA: Wexley (Oct-25 to Jun-26) | B12: 932000 | C12: Buy-side QoE
A13: Selling partner compensation normalization | B13: =E24 -> 291666.67 | C13: See schedule below
A14: Integration costs | B14: ='Monthly Trend'!K35 -> 405000 | C14: Systems migration and integration staff
A15: Transaction costs | B15: ='Monthly Trend'!K36 -> 215000 | C15: Acquisitions and pipeline diligence
A16: Sponsor monitoring fee | B16: ='Monthly Trend'!K37 -> 315000 | C16: Jan to Sep 2026
A17: LTM Pro Forma Adjusted EBITDA | B17: =SUM(B8:B16) -> 7941214.7
A19: Schedule: selling partner compensation normalization
A20: Partner | B20: Practice | C20: Current annual comp ($) | D20: Pro forma comp per purchase agreement ($) | E20: LTM normalization ($) | F20: Comp reset effective | G20: Months owned in LTM
A21: Selling Partner RF-01 | B21: Redfern (acq. Mar-26) | C21: 560000 | D21: 300000 | E21: =(C21-D21)*G21/12 -> 151666.67 | F21: Jan 1, 2027 | G21: 7
A22: Selling Partner RF-02 | B22: Redfern (acq. Mar-26) | C22: 540000 | D22: 300000 | E22: =(C22-D22)*G22/12 -> 140000 | F22: Jan 1, 2027 | G22: 7
A23: Ashcombe and Wexley selling partners were reset to pro forma compensation at closing.
D24: Total | E24: =SUM(E21:E22) -> 291666.67

Sheet People & Utilization
A1: TALLIS BROOK ACCOUNTING GROUP
A2: Headcount, Chargeable Hours and Utilization, September 2026
A3: Hours and headcount; available hours = 168 per person in September | Synthetic test data. Fictional firm and clients; not based on any real business.
A5: Practice | B5: Level | C5: Headcount | D5: Available hours | E5: Chargeable hours | F5: Utilization | G5: Standard rate ($/hr) | H5: Standard value of time ($) | I5: Voluntary departures (LTM) | J5: Selling partner?
A6: Tallis Brook (legacy) | B6: Partner | C6: 6 | D6: =C6*168 -> 1008 | E6: 490 | F6: =IF(D6=0,0,E6/D6) -> 0.48611111 | G6: 425 | H6: =E6*G6 -> 208250 | I6: 0
A7: Tallis Brook (legacy) | B7: Manager | C7: 18 | D7: =C7*168 -> 3024 | E7: 2032 | F7: =IF(D7=0,0,E7/D7) -> 0.67195767 | G7: 285 | H7: =E7*G7 -> 579120 | I7: 1
A8: Tallis Brook (legacy) | B8: Senior | C8: 28 | D8: =C8*168 -> 4704 | E8: 3493 | F8: =IF(D8=0,0,E8/D8) -> 0.74255952 | G8: 195 | H8: =E8*G8 -> 681135 | I8: 2
A9: Tallis Brook (legacy) | B9: Staff | C9: 34 | D9: =C9*168 -> 5712 | E9: 4343 | F9: =IF(D9=0,0,E9/D9) -> 0.76032913 | G9: 145 | H9: =E9*G9 -> 629735 | I9: 4
A10: Tallis Brook (legacy) | B10: Admin & support | C10: 14 | I10: 2
A11: Tallis Brook (legacy) total | C11: =SUM(C6:C10) -> 100 | D11: =SUM(D6:D10) -> 14448 | E11: =SUM(E6:E10) -> 10358 | F11: =IF(D11=0,0,E11/D11) -> 0.71691584 | H11: =SUM(H6:H10) -> 2098240 | I11: =SUM(I6:I10) -> 9
A13: Ashcombe (acq. Nov-25) | B13: Partner | C13: 2 | D13: =C13*168 -> 336 | E13: 141 | F13: =IF(D13=0,0,E13/D13) -> 0.41964286 | G13: 425 | H13: =E13*G13 -> 59925 | I13: 1 | J13: Yes (2 of 2)
A14: Ashcombe (acq. Nov-25) | B14: Manager | C14: 6 | D14: =C14*168 -> 1008 | E14: 608 | F14: =IF(D14=0,0,E14/D14) -> 0.6031746 | G14: 285 | H14: =E14*G14 -> 173280 | I14: 2
A15: Ashcombe (acq. Nov-25) | B15: Senior | C15: 9 | D15: =C15*168 -> 1512 | E15: 1013 | F15: =IF(D15=0,0,E15/D15) -> 0.66997354 | G15: 195 | H15: =E15*G15 -> 197535 | I15: 3
A16: Ashcombe (acq. Nov-25) | B16: Staff | C16: 11 | D16: =C16*168 -> 1848 | E16: 1268 | F16: =IF(D16=0,0,E16/D16) -> 0.68614719 | G16: 145 | H16: =E16*G16 -> 183860 | I16: 4
A17: Ashcombe (acq. Nov-25) | B17: Admin & support | C17: 5 | I17: 2
A18: Ashcombe (acq. Nov-25) total | C18: =SUM(C13:C17) -> 33 | D18: =SUM(D13:D17) -> 4704 | E18: =SUM(E13:E17) -> 3030 | F18: =IF(D18=0,0,E18/D18) -> 0.64413265 | H18: =SUM(H13:H17) -> 614600 | I18: =SUM(I13:I17) -> 12
A20: Redfern (acq. Mar-26) | B20: Partner | C20: 3 | D20: =C20*168 -> 504 | E20: 234 | F20: =IF(D20=0,0,E20/D20) -> 0.46428571 | G20: 425 | H20: =E20*G20 -> 99450 | I20: 0 | J20: Yes (2 of 3)
A21: Redfern (acq. Mar-26) | B21: Manager | C21: 7 | D21: =C21*168 -> 1176 | E21: 750 | F21: =IF(D21=0,0,E21/D21) -> 0.6377551 | G21: 285 | H21: =E21*G21 -> 213750 | I21: 2
A22: Redfern (acq. Mar-26) | B22: Senior | C22: 9 | D22: =C22*168 -> 1512 | E22: 1023 | F22: =IF(D22=0,0,E22/D22) -> 0.6765873 | G22: 195 | H22: =E22*G22 -> 199485 | I22: 4
A23: Redfern (acq. Mar-26) | B23: Staff | C23: 12 | D23: =C23*168 -> 2016 | E23: 1384 | F23: =IF(D23=0,0,E23/D23) -> 0.68650794 | G23: 145 | H23: =E23*G23 -> 200680 | I23: 5
A24: Redfern (acq. Mar-26) | B24: Admin & support | C24: 5 | I24: 1
A25: Redfern (acq. Mar-26) total | C25: =SUM(C20:C24) -> 36 | D25: =SUM(D20:D24) -> 5208 | E25: =SUM(E20:E24) -> 3391 | F25: =IF(D25=0,0,E25/D25) -> 0.65111367 | H25: =SUM(H20:H24) -> 713365 | I25: =SUM(I20:I24) -> 12
A27: Wexley (acq. Jul-26) | B27: Partner | C27: 2 | D27: =C27*168 -> 336 | E27: 148 | F27: =IF(D27=0,0,E27/D27) -> 0.44047619 | G27: 425 | H27: =E27*G27 -> 62900 | I27: 0 | J27: Yes (2 of 2)
A28: Wexley (acq. Jul-26) | B28: Manager | C28: 5 | D28: =C28*168 -> 840 | E28: 499 | F28: =IF(D28=0,0,E28/D28) -> 0.59404762 | G28: 285 | H28: =E28*G28 -> 142215 | I28: 0
A29: Wexley (acq. Jul-26) | B29: Senior | C29: 8 | D29: =C29*168 -> 1344 | E29: 884 | F29: =IF(D29=0,0,E29/D29) -> 0.6577381 | G29: 195 | H29: =E29*G29 -> 172380 | I29: 1
A30: Wexley (acq. Jul-26) | B30: Staff | C30: 9 | D30: =C30*168 -> 1512 | E30: 1019 | F30: =IF(D30=0,0,E30/D30) -> 0.6739418 | G30: 145 | H30: =E30*G30 -> 147755 | I30: 1
A31: Wexley (acq. Jul-26) | B31: Admin & support | C31: 4 | I31: 0
A32: Wexley (acq. Jul-26) total | C32: =SUM(C27:C31) -> 28 | D32: =SUM(D27:D31) -> 4032 | E32: =SUM(E27:E31) -> 2550 | F32: =IF(D32=0,0,E32/D32) -> 0.63244048 | H32: =SUM(H27:H31) -> 525250 | I32: =SUM(I27:I31) -> 2
A34: Corporate (finance, HR, IT, integration) | C34: 15
A35: Total firm headcount | C35: =C11+C18+C25+C32+C34 -> 212
A36: Offshore delivery team (contracted FTEs, not in headcount) | C36: 12

Sheet WIP AR Realization
A1: TALLIS BROOK ACCOUNTING GROUP
A2: Realization, Work in Process and Receivables, September 2026
A3: US dollars | Synthetic test data. Fictional firm and clients; not based on any real business.
A5: Measure | B5: Tallis Brook (legacy) | C5: Ashcombe (acq. Nov-25) | D5: Redfern (acq. Mar-26) | E5: Wexley (acq. Jul-26) | F5: Firm total
A6: Realization (September)
A7: Standard value of time | B7: ='People & Utilization'!H11 -> 2098240 | C7: ='People & Utilization'!H18 -> 614600 | D7: ='People & Utilization'!H25 -> 713365 | E7: ='People & Utilization'!H32 -> 525250 | F7: =SUM(B7:E7) -> 3951455
A8: Net fee revenue | B8: ='Practice P&L'!B12 -> 1909330 | C8: ='Practice P&L'!C12 -> 540553 | D8: ='Practice P&L'!D12 -> 542218 | E8: ='Practice P&L'!E12 -> 483317 | F8: =SUM(B8:E8) -> 3475418
A9: Realization (revenue / standard value) | B9: =IF(B7=0,0,B8/B7) -> 0.9099674 | C9: =IF(C7=0,0,C8/C7) -> 0.87952001 | D9: =IF(D7=0,0,D8/D7) -> 0.76008495 | E9: =IF(E7=0,0,E8/E7) -> 0.92016564 | F9: =IF(F7=0,0,F8/F7) -> 0.87952868
A10: Write-downs, YTD 2026 | B10: 118000 | C10: 96000 | D10: 412000 | E10: 14000 | F10: =SUM(B10:E10) -> 640000
A12: Work in process (unbilled time) aging
A13: WIP 0-30 days | B13: 897000 | C13: 296400 | D13: 254800 | E13: 222300 | F13: =SUM(B13:E13) -> 1670500
A14: WIP 31-60 days | B14: 405600 | C14: 135200 | D14: 196300 | E14: 75400 | F14: =SUM(B14:E14) -> 812500
A15: WIP 61-90 days | B15: 153400 | C15: 61100 | D15: 158600 | E15: 15600 | F15: =SUM(B15:E15) -> 388700
A16: WIP 91-120 days | B16: 67600 | C16: 36400 | D16: 141700 | E16: 0 | F16: =SUM(B16:E16) -> 245700
A17: WIP Over 120 days | B17: 53300 | C17: 28600 | D17: 413400 | E17: 0 | F17: =SUM(B17:E17) -> 495300
A18: Total WIP | B18: =SUM(B13:B17) -> 1576900 | C18: =SUM(C13:C17) -> 557700 | D18: =SUM(D13:D17) -> 1164800 | E18: =SUM(E13:E17) -> 313300 | F18: =SUM(B18:E18) -> 3612700
A20: Accounts receivable aging
A21: AR Current | B21: 1313000 | C21: 439400 | D21: 391300 | E21: 317200 | F21: =SUM(B21:E21) -> 2460900
A22: AR 31-60 days | B22: 522600 | C22: 183300 | D22: 178100 | E22: 79300 | F22: =SUM(B22:E22) -> 963300
A23: AR 61-90 days | B23: 215800 | C23: 93600 | D23: 114400 | E23: 11700 | F23: =SUM(B23:E23) -> 435500
A24: AR Over 90 days | B24: 127400 | C24: 79300 | D24: 124800 | E24: 0 | F24: =SUM(B24:E24) -> 331500
A25: Total AR | B25: =SUM(B21:B24) -> 2178800 | C25: =SUM(C21:C24) -> 795600 | D25: =SUM(D21:D24) -> 808600 | E25: =SUM(E21:E24) -> 408200 | F25: =SUM(B25:E25) -> 4191200
A27: Lockup (Q3 2026 revenue annualized)
A28: Q3 2026 net fee revenue | B28: 4387709 | C28: 1184232 | D28: 1176183 | E28: 1056881 | F28: =SUM(B28:E28) -> 7805005
A29: WIP days | B29: =IF(B28=0,0,B18/(B28*4/365)) -> 32.794364 | C29: =IF(C28=0,0,C18/(C28*4/365)) -> 42.973104 | D29: =IF(D28=0,0,D18/(D28*4/365)) -> 90.36689 | E29: =IF(E28=0,0,E18/(E28*4/365)) -> 27.049994 | F29: =IF(F28=0,0,F18/(F28*4/365)) -> 42.236856
A30: Days sales outstanding | B30: =IF(B28=0,0,B25/(B28*4/365)) -> 45.311916 | C30: =IF(C28=0,0,C25/(C28*4/365)) -> 61.304288 | D30: =IF(D28=0,0,D25/(D28*4/365)) -> 62.732372 | E30: =IF(E28=0,0,E25/(E28*4/365)) -> 35.243561 | F30: =IF(F28=0,0,F25/(F28*4/365)) -> 49.000225
A31: Lockup days (WIP days + DSO) | B31: =B29+B30 -> 78.106279 | C31: =C29+C30 -> 104.27739 | D31: =D29+D30 -> 153.09926 | E31: =E29+E30 -> 62.293555 | F31: =F29+F30 -> 91.237081
A33: Note: Wexley was acquired July 1, 2026; its WIP and AR exclude balances retained by the sellers at closing.

Sheet Client Book
A1: TALLIS BROOK ACCOUNTING GROUP
A2: Client Book: Retention and Largest Relationships
A3: US dollars; LTM = October 2025 to September 2026 | Synthetic test data. Fictional firm and clients; not based on any real business.
A5: Practice | B5: Clients at Oct 1, 2025 (or acquisition) | C5: Clients lost since | D5: Clients added | E5: Clients at Sep 30, 2026 | F5: Gross retention
A6: Tallis Brook (legacy) | B6: 1420 | C6: 52 | D6: 118 | E6: =B6-C6+D6 -> 1486 | F6: =IF(B6=0,0,1-C6/B6) -> 0.96338028
A7: Ashcombe (acq. Nov-25) | B7: 610 | C7: 98 | D7: 21 | E7: =B7-C7+D7 -> 533 | F7: =IF(B7=0,0,1-C7/B7) -> 0.83934426
A8: Redfern (acq. Mar-26) | B8: 480 | C8: 21 | D8: 9 | E8: =B8-C8+D8 -> 468 | F8: =IF(B8=0,0,1-C8/B8) -> 0.95625
A9: Wexley (acq. Jul-26) | B9: 355 | C9: 2 | D9: 4 | E9: =B9-C9+D9 -> 357 | F9: =IF(B9=0,0,1-C9/B9) -> 0.9943662
A10: Firm total | B10: =SUM(B6:B9) -> 2865 | C10: =SUM(C6:C9) -> 173 | D10: =SUM(D6:D9) -> 152 | E10: =SUM(E6:E9) -> 2844 | F10: =IF(B10=0,0,1-C10/B10) -> 0.93961606
A12: Client | B12: Practice | C12: Industry | D12: Primary services | E12: Relationship partner | F12: LTM fees ($) | G12: Status | H12: Notes
A13: Client 1001 | B13: Tallis Brook (legacy) | C13: Manufacturing | D13: Audit, Tax | E13: LP-01 | F13: 412000 | G13: Active
A14: Client 1002 | B14: Tallis Brook (legacy) | C14: Real estate partnerships | D14: Tax | E14: LP-02 | F14: 368000 | G14: Active
A15: Client 1003 | B15: Tallis Brook (legacy) | C15: Healthcare practice | D15: CAS, Tax | E15: LP-03 | F15: 296000 | G15: Active
A16: Client 2001 | B16: Ashcombe (acq. Nov-25) | C16: Family office | D16: Tax, Trust | E16: AS-01 (retired May-26) | F16: 284000 | G16: Departed Aug-26 | H16: Moved with former partner's referral
A17: Client 1004 | B17: Tallis Brook (legacy) | C17: Construction | D17: Audit, Tax | E17: LP-01 | F17: 271000 | G17: Active
A18: Client 3001 | B18: Redfern (acq. Mar-26) | C18: Distribution | D18: Audit, Tax | E18: RF-01 | F18: 254000 | G18: Active | H18: Fixed-fee engagement
A19: Client 2002 | B19: Ashcombe (acq. Nov-25) | C19: Dental group | D19: CAS, Tax | E19: AS-01 (retired May-26) | F19: 198000 | G19: Departed Jul-26
A20: Client 1005 | B20: Tallis Brook (legacy) | C20: Nonprofit | D20: Audit | E20: LP-04 | F20: 187000 | G20: Active
A21: Client 3002 | B21: Redfern (acq. Mar-26) | C21: Professional services | D21: CAS, Tax | E21: RF-02 | F21: 176000 | G21: Active | H21: Fixed-fee engagement
A22: Client 4001 | B22: Wexley (acq. Jul-26) | C22: Agriculture | D22: Tax, Advisory | E22: WX-01 | F22: 164000 | G22: Active
A23: Client 2003 | B23: Ashcombe (acq. Nov-25) | C23: Restaurant group | D23: Tax | E23: AS-01 (retired May-26) | F23: 152000 | G23: Notice given Sep-26 | H23: Engagement letter not renewed for 2027
A24: Client 1006 | B24: Tallis Brook (legacy) | C24: Technology | D24: CAS, Advisory | E24: LP-05 | F24: 149000 | G24: Active | H24: CAS client since 2024
A25: Client 3003 | B25: Redfern (acq. Mar-26) | C25: Senior living | D25: Audit | E25: RF-01 | F25: 141000 | G25: Active | H25: Fixed-fee engagement
A26: Client 1007 | B26: Tallis Brook (legacy) | C26: Auto dealerships | D26: Tax | E26: LP-02 | F26: 138000 | G26: Active
A27: Client 4002 | B27: Wexley (acq. Jul-26) | C27: Construction | D27: Audit, Tax | E27: WX-02 | F27: 131000 | G27: Active
